<?xml version="1.0" encoding="utf-8" ?>
<dwsync>
<file name="admin.js" server="c1481017.ferozo.com/public_html/" local="130805587610000000" remote="131967269400000000" Dst="0" />
<file name="core.js" server="c1481017.ferozo.com/public_html/" local="130805605880000000" remote="131967269400000000" Dst="0" />
<file name="html5-min.js" server="c1481017.ferozo.com/public_html/" local="130480221050000000" remote="131967269400000000" Dst="0" />
<file name="html5.js" server="c1481017.ferozo.com/public_html/" local="130816956420000000" remote="131967269400000000" Dst="0" />
<file name="gallery.js" server="c1481017.ferozo.com/public_html/" local="130805612170000000" remote="131967269400000000" Dst="0" />
<file name="jquery-cycle2.js" server="c1481017.ferozo.com/public_html/" local="130816954790000000" remote="131967269400000000" Dst="0" />
<file name="jquery-cycle2-min.js" server="c1481017.ferozo.com/public_html/" local="130762461910000000" remote="131967269400000000" Dst="0" />
<file name="jquery-magnific-min.js" server="c1481017.ferozo.com/public_html/" local="130819412890000000" remote="131967269400000000" Dst="0" />
<file name="jquery-magnific.js" server="c1481017.ferozo.com/public_html/" local="130816957060000000" remote="131967269400000000" Dst="0" />
</dwsync>